colacloud_cli/__init__.py
colacloud_cli/api.py
colacloud_cli/config.py
colacloud_cli/formatters.py
colacloud_cli/main.py
colacloud_cli/commands/__init__.py
colacloud_cli/commands/barcode.py
colacloud_cli/commands/colas.py
colacloud_cli/commands/config.py
colacloud_cli/commands/permittees.py
colacloud_cli/commands/usage.py
colacloud_cli/commands/utils.py
colacloud_cli-0.1.0.dist-info/METADATA
colacloud_cli-0.1.0.dist-info/WHEEL
colacloud_cli-0.1.0.dist-info/entry_points.txt
colacloud_cli-0.1.0.dist-info/licenses/LICENSE
colacloud_cli-0.1.0.dist-info/RECORD
