Metadata-Version: 2.4
Name: colacloud-cli
Version: 0.1.0
Summary: Command-line interface for the COLA Cloud API
Project-URL: Homepage, https://colacloud.us
Project-URL: Documentation, https://colacloud.us/docs/api
Project-URL: Repository, https://github.com/cola-cloud-us/colacloud-cli
Author-email: Jay Sobel <jay@colacloud.us>
License: MIT
License-File: LICENSE
Keywords: alcohol,cli,cola,labels,ttb
Classifier: Development Status :: 3 - Alpha
Classifier: Environment :: Console
Classifier: Intended Audience :: Developers
Classifier: License :: OSI Approved :: MIT License
Classifier: Operating System :: OS Independent
Classifier: Programming Language :: Python :: 3
Classifier: Programming Language :: Python :: 3.10
Classifier: Programming Language :: Python :: 3.11
Classifier: Programming Language :: Python :: 3.12
Classifier: Topic :: Utilities
Requires-Python: >=3.10
Requires-Dist: click>=8.1.0
Requires-Dist: httpx>=0.25.0
Requires-Dist: rich>=13.0.0
